{
    "profile_name": "Profile Example",
    "profile_slug": "{{ cookiecutter.profile_name|slugify }}",
    "optional_toml_linting": ["true", "false"],
    "optional_workflow_linting": ["true", "false"],
    "description": "An example Mac Maker profile.",
    "github_handle": "osx-provisioner",
    "author": "Niall Byrne",
    "email": "niall@niallbyrne.ca",
    "_copy_without_render": [
        "profile/vars/*.yml",
        "profile/tasks/post_install/*.yml",
        "profile/handlers/*.yml"
    ],
    "_BRANCH_NAME_BASE": "master",
    "_BRANCH_NAME_DEVELOPMENT": "dev",
    "_GITHUB_ACTION_CACHE": "actions/cache@v3",
    "_GITHUB_ACTION_CHECKOUT": "actions/checkout@v3",
    "_GITHUB_ACTION_MARKDOWN_LINK_CHECK": "gaurav-nelson/github-action-markdown-link-check@v1",
    "_GITHUB_ACTION_PYTHON": "actions/setup-python@v4",
    "_GITHUB_ACTION_SCRIPT": "actions/github-script@v6",
    "_GITHUB_ACTION_TRUFFLEHOG": "trufflesecurity/trufflehog@v3.20.0",
    "_GITHUB_ACTION_YAMLLINT": "ibiqlik/action-yamllint@v3",
    "_GITHUB_CI_ACTIONLINT_SCRIPT_URL": "https://raw.githubusercontent.com/rhysd/actionlint/main/scripts/download-actionlint.bash",
    "_GITHUB_CI_DEFAULT_CONCURRENCY": 4,
    "_GITHUB_CI_DEFAULT_VERBOSE_NOTIFICATIONS": false,
    "_GITHUB_CI_TEMPLATE_TEST_ARCHITECTURES": ["x86_64"],
    "_GITHUB_CI_TEMPLATE_TEST_OSX_VERSIONS": [12],
    "_MAC_MAKER_ANSIBLE_VERSION": "7.2",
    "_MAC_MAKER_MAX_VERSION": "1.0.0",
    "_MAC_MAKER_MIN_VERSION": "0.0.6",
    "_MAC_MAKER_PYTHON_VERSION": "3.9",
    "*DO_NOT_MODIFY_THIS_FILE*": "This file is created to assist with upgrading to future versions of this template."
}
